mb_ffmpeg/__init__.py
mb_ffmpeg/advanced_ops.py
mb_ffmpeg/audio_ops.py
mb_ffmpeg/base.py
mb_ffmpeg/basic_ops.py
mb_ffmpeg/version.py
mb_ffmpeg/video_ops.py
mb_ffmpeg-1.0.16.dist-info/METADATA
mb_ffmpeg-1.0.16.dist-info/WHEEL
mb_ffmpeg-1.0.16.dist-info/top_level.txt
mb_ffmpeg-1.0.16.dist-info/RECORD
