Metadata-Version: 2.4
Name: mb_ffmpeg
Version: 1.0.16
Summary: FFMPEG function python file
Author: ['Malav Bateriwala']
Requires-Python: >=3.8
Dynamic: author
Dynamic: requires-python
Dynamic: summary
